LICENSE
README.md
setup.cfg
setup.py
rfpy/__init__.py
rfpy/binning.py
rfpy/ccp.py
rfpy/harmonics.py
rfpy/hk.py
rfpy/plotting.py
rfpy/rfdata.py
rfpy/utils.py
rfpy.egg-info/PKG-INFO
rfpy.egg-info/SOURCES.txt
rfpy.egg-info/dependency_links.txt
rfpy.egg-info/entry_points.txt
rfpy.egg-info/requires.txt
rfpy.egg-info/top_level.txt
rfpy/scripts/__init__.py
rfpy/scripts/rfpy_calc.py
rfpy/scripts/rfpy_ccp.py
rfpy/scripts/rfpy_harmonics.py
rfpy/scripts/rfpy_hk.py
rfpy/scripts/rfpy_plot.py
rfpy/scripts/rfpy_recalc.py
rfpy/tests/__init__.py
rfpy/tests/test_imports.py