Metadata-Version: 2.1
Name: rfpy
Version: 0.1.2
Summary: Python Module for Teleseismic Receiver Functions
Home-page: https://github.com/paudetseis/RfPy
Author: Pascal Audet
Author-email: pascal.audet@uottawa.ca
Maintainer: Pascal Audet
Maintainer-email: pascal.audet@uottawa.ca
License: UNKNOWN
Platform: UNKNOWN
Classifier: Development Status :: 3 - Alpha
Classifier: License :: OSI Approved :: MIT License
Classifier: Programming Language :: Python :: 3.6
Classifier: Programming Language :: Python :: 3.7
Classifier: Programming Language :: Python :: 3.8
Classifier: Programming Language :: Python :: 3.9
Classifier: Programming Language :: Python :: 3.10
Requires-Python: >=3.7
License-File: LICENSE
